{
  "configVersion": 1,
  "timestamp": 1721189202664,
  "index": "https://bm9999nd.github.io/portfolio/index.html",
  "assetGroups": [
    {
      "name": "app",
      "installMode": "prefetch",
      "updateMode": "prefetch",
      "cacheQueryOptions": {
        "ignoreVary": true
      },
      "urls": [
        "https://bm9999nd.github.io/portfolio/chunk-37RVO6ZK.js",
        "https://bm9999nd.github.io/portfolio/chunk-3CHKO3HY.js",
        "https://bm9999nd.github.io/portfolio/chunk-3RXH3EC2.js",
        "https://bm9999nd.github.io/portfolio/chunk-4MNFZP5U.js",
        "https://bm9999nd.github.io/portfolio/chunk-7I42KOIW.js",
        "https://bm9999nd.github.io/portfolio/chunk-A3VVPZ43.js",
        "https://bm9999nd.github.io/portfolio/chunk-AOHIV22S.js",
        "https://bm9999nd.github.io/portfolio/chunk-BS3HF5NJ.js",
        "https://bm9999nd.github.io/portfolio/chunk-BSDHREMJ.js",
        "https://bm9999nd.github.io/portfolio/chunk-DTJTL3FL.js",
        "https://bm9999nd.github.io/portfolio/chunk-FTEEZ7PL.js",
        "https://bm9999nd.github.io/portfolio/chunk-FTRD6JFR.js",
        "https://bm9999nd.github.io/portfolio/chunk-IRTEO7P6.js",
        "https://bm9999nd.github.io/portfolio/chunk-JN6HCPUQ.js",
        "https://bm9999nd.github.io/portfolio/chunk-KVYSHGQH.js",
        "https://bm9999nd.github.io/portfolio/chunk-LD3OHDNX.js",
        "https://bm9999nd.github.io/portfolio/chunk-LDPW326Q.js",
        "https://bm9999nd.github.io/portfolio/chunk-LRJRMM34.js",
        "https://bm9999nd.github.io/portfolio/chunk-Q7PKOSKL.js",
        "https://bm9999nd.github.io/portfolio/chunk-RP5JQW6L.js",
        "https://bm9999nd.github.io/portfolio/chunk-T7X37A3L.js",
        "https://bm9999nd.github.io/portfolio/chunk-W5TYH3OE.js",
        "https://bm9999nd.github.io/portfolio/favicon.ico",
        "https://bm9999nd.github.io/portfolio/index.html",
        "https://bm9999nd.github.io/portfolio/main-ZIAJYYHD.js",
        "https://bm9999nd.github.io/portfolio/manifest.webmanifest",
        "https://bm9999nd.github.io/portfolio/polyfills-6EAL64PA.js",
        "https://bm9999nd.github.io/portfolio/styles-TQGJJAPE.css"
      ],
      "patterns": []
    },
    {
      "name": "assets",
      "installMode": "lazy",
      "updateMode": "prefetch",
      "cacheQueryOptions": {
        "ignoreVary": true
      },
      "urls": [
        "https://bm9999nd.github.io/portfolio/assets/1708105683281.jpeg",
        "https://bm9999nd.github.io/portfolio/assets/cash-web.jpg",
        "https://bm9999nd.github.io/portfolio/assets/icons/icon-128x128.png",
        "https://bm9999nd.github.io/portfolio/assets/icons/icon-144x144.png",
        "https://bm9999nd.github.io/portfolio/assets/icons/icon-152x152.png",
        "https://bm9999nd.github.io/portfolio/assets/icons/icon-192x192.png",
        "https://bm9999nd.github.io/portfolio/assets/icons/icon-384x384.png",
        "https://bm9999nd.github.io/portfolio/assets/icons/icon-512x512.png",
        "https://bm9999nd.github.io/portfolio/assets/icons/icon-72x72.png",
        "https://bm9999nd.github.io/portfolio/assets/icons/icon-96x96.png",
        "https://bm9999nd.github.io/portfolio/assets/mobile-web.png",
        "https://bm9999nd.github.io/portfolio/assets/slash-tag.ico"
      ],
      "patterns": []
    }
  ],
  "dataGroups": [],
  "hashTable": {
    "https://bm9999nd.github.io/portfolio/assets/1708105683281.jpeg": "26f0bd0599f5d24552e52b03508d34d123b9a1bc",
    "https://bm9999nd.github.io/portfolio/assets/cash-web.jpg": "a4955991ad04e97777fbf3c7bebac4d3b9865cb4",
    "https://bm9999nd.github.io/portfolio/assets/icons/icon-128x128.png": "6cdb65df4f3102bcf1c23beed28a6e2fb9d7b43b",
    "https://bm9999nd.github.io/portfolio/assets/icons/icon-144x144.png": "5539abd816655c5c74b4ca2bf6cf09b87257a9f4",
    "https://bm9999nd.github.io/portfolio/assets/icons/icon-152x152.png": "a47603dceb4d1beccfc14a28fc96c4b30e3794c5",
    "https://bm9999nd.github.io/portfolio/assets/icons/icon-192x192.png": "adc4037742c060e62e478597039206f712a25bdd",
    "https://bm9999nd.github.io/portfolio/assets/icons/icon-384x384.png": "9ac112d28eabab6be920b733872c9814f4e6423d",
    "https://bm9999nd.github.io/portfolio/assets/icons/icon-512x512.png": "c73ee0966b344d8d57885b047c012b219b3558f2",
    "https://bm9999nd.github.io/portfolio/assets/icons/icon-72x72.png": "9cc7a7c842e6ee46885c2ead9deca2724c76e369",
    "https://bm9999nd.github.io/portfolio/assets/icons/icon-96x96.png": "d72be80b94af291fe917c228cf96e62be48d7002",
    "https://bm9999nd.github.io/portfolio/assets/mobile-web.png": "c655b3ddb6afe73e0091750a9200c7c261cd863a",
    "https://bm9999nd.github.io/portfolio/assets/slash-tag.ico": "0a5845d4b012562a68f30e87f3cb8f5ebeddae32",
    "https://bm9999nd.github.io/portfolio/chunk-37RVO6ZK.js": "8c1ce464597b93e7a1fcc296f8799a8557e0714a",
    "https://bm9999nd.github.io/portfolio/chunk-3CHKO3HY.js": "4ae7d8c3df9aa3747d135c045cad016eaec98bea",
    "https://bm9999nd.github.io/portfolio/chunk-3RXH3EC2.js": "c053fc25671c1ca82509bafcdea03658c3f93a31",
    "https://bm9999nd.github.io/portfolio/chunk-4MNFZP5U.js": "4a431c5ebdda656bd4dbc88dd6b4108d45c0bfe3",
    "https://bm9999nd.github.io/portfolio/chunk-7I42KOIW.js": "99a29ba6d0c076a12f092b174932464157881aa0",
    "https://bm9999nd.github.io/portfolio/chunk-A3VVPZ43.js": "970e68f3f6f0938b1d8cc5246588efc4c736501a",
    "https://bm9999nd.github.io/portfolio/chunk-AOHIV22S.js": "1e11a156416eb3d8ab4dc92dddad68cf21f0a55a",
    "https://bm9999nd.github.io/portfolio/chunk-BS3HF5NJ.js": "bc44b3324ca6c0de6df2653ab459b08bc3599d06",
    "https://bm9999nd.github.io/portfolio/chunk-BSDHREMJ.js": "6c3c37eccc2f4030440b9f6788a58d5d2f57c753",
    "https://bm9999nd.github.io/portfolio/chunk-DTJTL3FL.js": "97ee0113ae46a8914f0e7ff93813e724c9d4f21d",
    "https://bm9999nd.github.io/portfolio/chunk-FTEEZ7PL.js": "f0c4e5da9c08f9cb8449396282f52f1ecd642836",
    "https://bm9999nd.github.io/portfolio/chunk-FTRD6JFR.js": "6d0eb3b37b7ee845dbe089a6383b2998cde3671b",
    "https://bm9999nd.github.io/portfolio/chunk-IRTEO7P6.js": "6a79d0bd077212177b05b16abb2bd86cebb69465",
    "https://bm9999nd.github.io/portfolio/chunk-JN6HCPUQ.js": "aa531e20be17726c7ffe100826b11a52d355f5c0",
    "https://bm9999nd.github.io/portfolio/chunk-KVYSHGQH.js": "c9efa21b25f01139164335189360720a70539b2c",
    "https://bm9999nd.github.io/portfolio/chunk-LD3OHDNX.js": "b30cc5e96fbfb7ffad39ff029851c61ae73d9cc4",
    "https://bm9999nd.github.io/portfolio/chunk-LDPW326Q.js": "24322f63cc654bce70023330819ebffd0cd5072f",
    "https://bm9999nd.github.io/portfolio/chunk-LRJRMM34.js": "1eaee6a62be881c53eb43379914bfb20ced78f2a",
    "https://bm9999nd.github.io/portfolio/chunk-Q7PKOSKL.js": "9b2f90eac20190a199450ee882d43bf73bc9a711",
    "https://bm9999nd.github.io/portfolio/chunk-RP5JQW6L.js": "4e78e8c5fa989bf47b027c873fb7481e253fd3df",
    "https://bm9999nd.github.io/portfolio/chunk-T7X37A3L.js": "4f8cae5f8c464607c7b7e9f2903bec19f28e51a5",
    "https://bm9999nd.github.io/portfolio/chunk-W5TYH3OE.js": "c1e0ae13c00713453cf3f3b11b491191d3e5c867",
    "https://bm9999nd.github.io/portfolio/favicon.ico": "9c39f434fe1261f68c5e3eefdf734630d99c5670",
    "https://bm9999nd.github.io/portfolio/index.html": "f3a1407c1bc37ccd87b212806b02ccc745dea18d",
    "https://bm9999nd.github.io/portfolio/main-ZIAJYYHD.js": "e2c0c7dbe595d9e866d8386c5259d3b35e6dc30d",
    "https://bm9999nd.github.io/portfolio/manifest.webmanifest": "e14484a4f652e2f158ec8045c44ef1b6d61e9f2d",
    "https://bm9999nd.github.io/portfolio/polyfills-6EAL64PA.js": "d874147a12a6570d9b44e99935e9de8b7f3cabbc",
    "https://bm9999nd.github.io/portfolio/styles-TQGJJAPE.css": "f62fb7ead5f426f0ed28fd727eaf1a1f69bbe690"
  },
  "navigationUrls": [
    {
      "positive": true,
      "regex": "^\\/.*$"
    },
    {
      "positive": false,
      "regex": "^\\/(?:.+\\/)?[^/]*\\.[^/]*$"
    },
    {
      "positive": false,
      "regex": "^\\/(?:.+\\/)?[^/]*__[^/]*$"
    },
    {
      "positive": false,
      "regex": "^\\/(?:.+\\/)?[^/]*__[^/]*\\/.*$"
    }
  ],
  "navigationRequestStrategy": "performance"
}